test_plan_megaexporter/__init__.py
test_plan_megaexporter/models.py
test_plan_megaexporter/selectors.py
test_plan_megaexporter/serializers.py
test_plan_megaexporter/tasks.py
test_plan_megaexporter/urls.py
test_plan_megaexporter/views.py
test_plan_megaexporter/migrations/0001_initial.py
test_plan_megaexporter/migrations/0002_alter_documentrequest_user_id.py
test_plan_megaexporter/migrations/__init__.py
test_plan_megaexporter/report/__init__.py
test_plan_megaexporter/report/base.py
test_plan_megaexporter/report/common.py
test_plan_megaexporter/report/plan.py
test_plan_megaexporter/report/result.py
test_plan_megaexporter/report/builders/__init__.py
test_plan_megaexporter/report/builders/base_builders.py
test_plan_megaexporter/report/builders/complex_builders.py
test_plan_megaexporter/report/builders/markdown.py
test_plan_megaexporter/report/builders/table.py
test_plan_megaexporter/report/builders/utils.py
test_plan_megaexporter/static/test_plan_exporter/css/base.css
test_plan_megaexporter/static/test_plan_exporter/css/bootstrap.min.css
test_plan_megaexporter/static/test_plan_exporter/css/document-types.css
test_plan_megaexporter/static/test_plan_exporter/css/layout.css
test_plan_megaexporter/static/test_plan_exporter/css/loading.css
test_plan_megaexporter/static/test_plan_exporter/css/navigation.css
test_plan_megaexporter/static/test_plan_exporter/css/plan-tree.css
test_plan_megaexporter/static/test_plan_exporter/css/project-selector.css
test_plan_megaexporter/static/test_plan_exporter/css/responsive.css
test_plan_megaexporter/static/test_plan_exporter/css/steps.css
test_plan_megaexporter/static/test_plan_exporter/css/tree_checkboxes.css
test_plan_megaexporter/static/test_plan_exporter/fonts/Inter-VariableFont.ttf
test_plan_megaexporter/static/test_plan_exporter/img/default.png
test_plan_megaexporter/static/test_plan_exporter/img/logo.png
test_plan_megaexporter/static/test_plan_exporter/img/report_footer.png
test_plan_megaexporter-0.0.2.dist-info/METADATA
test_plan_megaexporter-0.0.2.dist-info/WHEEL
test_plan_megaexporter-0.0.2.dist-info/entry_points.txt
test_plan_megaexporter-0.0.2.dist-info/top_level.txt
test_plan_megaexporter-0.0.2.dist-info/RECORD
