Metadata-Version: 2.4
Name: test-plan-megaexporter
Version: 0.0.2
Summary: Export test plan and cases to PDF
Author-email: Ivan Dorodnitsyn <ivdorodnitsyn@gmail.com>
Project-URL: Homepage, https://github.com/evildarius/test-plan-megaexporter
Classifier: Programming Language :: Python :: 3
Classifier: License :: OSI Approved :: MIT License
Classifier: Operating System :: OS Independent
Requires-Python: >=3.11
Requires-Dist: requests>=2.28.0
Requires-Dist: reportlab
